xchange_mail/__init__.py
xchange_mail/handler.py
xchange_mail/mail.py
xchange_mail-0.0.7.dist-info/METADATA
xchange_mail-0.0.7.dist-info/WHEEL
xchange_mail-0.0.7.dist-info/top_level.txt
xchange_mail-0.0.7.dist-info/RECORD
